{
  "active": true,
  "connections": {
    "Code1": {
      "main": [
        [
          {
            "node": "Code3",
            "type": "main",
            "index": 0
          }
        ]
      ]
    },
    "Code3": {
      "main": [
        [
          {
            "node": "IF",
            "type": "main",
            "index": 0
          }
        ]
      ]
    },
    "IF": {
      "main": [
        [
          {
            "node": "Google Sheets",
            "type": "main",
            "index": 0
          }
        ],
        [
          {
            "node": "IF1",
            "type": "main",
            "index": 0
          }
        ]
      ]
    },
    "IF1": {
      "main": [
        [
          {
            "node": "Google Sheets2",
            "type": "main",
            "index": 0
          }
        ],
        [
          {
            "node": "IF2",
            "type": "main",
            "index": 0
          }
        ]
      ]
    },
    "Google Sheets": {
      "main": [
        [
          {
            "node": "Filter",
            "type": "main",
            "index": 0
          }
        ]
      ]
    },
    "Filter": {
      "main": [
        [
          {
            "node": "Google Sheets1",
            "type": "main",
            "index": 0
          }
        ]
      ]
    },
    "Google Sheets2": {
      "main": [
        [
          {
            "node": "Filter1",
            "type": "main",
            "index": 0
          }
        ]
      ]
    },
    "Filter1": {
      "main": [
        [
          {
            "node": "Google Sheets3",
            "type": "main",
            "index": 0
          }
        ]
      ]
    },
    "Google Sheets4": {
      "main": [
        [
          {
            "node": "Filter2",
            "type": "main",
            "index": 0
          }
        ]
      ]
    },
    "IF2": {
      "main": [
        [
          {
            "node": "Google Sheets4",
            "type": "main",
            "index": 0
          }
        ]
      ]
    },
    "Webhook": {
      "main": [
        [
          {
            "node": "Code1",
            "type": "main",
            "index": 0
          }
        ]
      ]
    },
    "Google Sheets1": {
      "main": [
        [
          {
            "node": "ENVIA C1",
            "type": "main",
            "index": 0
          }
        ]
      ]
    },
    "ENVIA C1": {
      "main": [
        [
          {
            "node": "ENVIA C1.1",
            "type": "main",
            "index": 0
          }
        ]
      ]
    },
    "ENVIA C1.1": {
      "main": [
        [
          {
            "node": "ENVIA C1.2",
            "type": "main",
            "index": 0
          }
        ]
      ]
    },
    "Google Sheets3": {
      "main": [
        [
          {
            "node": "ENVIA C",
            "type": "main",
            "index": 0
          }
        ]
      ]
    }
  },
  "createdAt": "2023-11-14T02:14:36.023Z",
  "id": "7w3pBcuja3Kgj4s9",
  "meta": null,
  "name": "[REUNIÃO SECRETA 7] - Cadência de Pesquisa",
  "nodes": [
    {
      "parameters": {
        "jsCode": "return typeof $node[\"Webhook\"].json[\"body\"] == 'string' ? JSON.parse($node[\"Webhook\"].json[\"body\"]) : $node[\"Webhook\"].json[\"body\"]\n"
      },
      "id": "9a605fb5-55e7-4e59-a072-02a1d5eb6f2b",
      "name": "Code1",
      "type": "n8n-nodes-base.code",
      "typeVersion": 1,
      "position": [
        660,
        460
      ]
    },
    {
      "parameters": {
        "jsCode": "function formataTelefone(number) {\n    number = number.toString().replace(/[^\\d]/g, \"\")\n    let ddi = '55'\n    let ddd = number.substring(0, 2)\n\n    if (number.length == 13) {\n        let ddi = number.substring(0, 2)\n        let ddd = number.substring(2, 4)\n        return ddi + ddd + (ddd <= 28 ? number.substring(4, 13) : number.substring(5, 13))\n\n    } else if (number.length == 11) {\n        return ddi + ddd + (ddd <= 28 ? number.substring(2, 11) : number.substring(3, 11))\n\n    } else if (number.length == 10) {\n        return ddi + ddd + (ddd <= 28 ? '9' : '') + number.substring(2, 11)\n\n    } else if (number.length == 12) {\n        return number.substring(0, 2) == '55' ? number : (number.substring(0, 1) == '0' ? formataTelefone(number.substring(1, 12)) : number)\n\n    } else {\n        return number\n    }\n}\n\n$input.all()[0].json['contact[phone]'] = formataTelefone($node['Code1'].json['contact[phone]'])\n\nreturn $input.all();"
      },
      "id": "7c91ebd0-d3d8-4edb-926b-333d5046025f",
      "name": "Code3",
      "type": "n8n-nodes-base.code",
      "typeVersion": 1,
      "position": [
        860,
        460
      ]
    },
    {
      "parameters": {
        "conditions": {
          "string": [
            {
              "value1": "={{ $json['contact[tags]'] }}",
              "operation": "contains",
              "value2": "RS7 Pesquisa - C1"
            },
            {
              "value1": "={{ $json['contact[tags]'] }}",
              "operation": "notContains",
              "value2": "RS7 Pesquisa - C2"
            },
            {
              "value1": "={{ $json['contact[tags]'] }}",
              "operation": "notContains",
              "value2": "RS7 Pesquisa - C3"
            }
          ]
        }
      },
      "id": "3ebed6e8-2d29-4a9a-ad5a-b28e5393dc02",
      "name": "IF",
      "type": "n8n-nodes-base.if",
      "typeVersion": 1,
      "position": [
        1060,
        460
      ]
    },
    {
      "parameters": {
        "documentId": {
          "__rl": true,
          "value": "130dJLqIJVkcFvqzEpK2M_bMpaGvhZMOLhDsWGuSJxy0",
          "mode": "list",
          "cachedResultName": "[ILA] [CICLO 3] Planilha Geral",
          "cachedResultUrl": "https://docs.google.com/spreadsheets/d/130dJLqIJVkcFvqzEpK2M_bMpaGvhZMOLhDsWGuSJxy0/edit?usp=drivesdk"
        },
        "sheetName": {
          "__rl": true,
          "value": 1930318114,
          "mode": "list",
          "cachedResultName": "[AUTO] Inscritos [AS7]",
          "cachedResultUrl": "https://docs.google.com/spreadsheets/d/130dJLqIJVkcFvqzEpK2M_bMpaGvhZMOLhDsWGuSJxy0/edit#gid=1930318114"
        },
        "filtersUI": {
          "values": [
            {
              "lookupColumn": "Email",
              "lookupValue": "={{ $('Code3').item.json['contact[email]'] }}"
            }
          ]
        },
        "options": {}
      },
      "id": "6bbc5790-b3ba-4af8-90a0-582937ae8702",
      "name": "Google Sheets",
      "type": "n8n-nodes-base.googleSheets",
      "typeVersion": 4,
      "position": [
        1420,
        320
      ],
      "alwaysOutputData": true,
      "credentials": {
        "googleSheetsOAuth2Api": {
          "id": "aqyCUOYp9QE28Sw2",
          "name": "Cris - Libertas"
        }
      }
    },
    {
      "parameters": {
        "conditions": {
          "string": [
            {
              "value1": "={{ $json['contact[tags]'] }}",
              "operation": "contains",
              "value2": "RS7 Pesquisa - C2"
            },
            {
              "value1": "={{ $json['contact[tags]'] }}",
              "operation": "notContains",
              "value2": "RS7 Pesquisa - C3"
            }
          ]
        }
      },
      "id": "9eeff2d7-8845-4efc-9a77-1645d95f3850",
      "name": "IF1",
      "type": "n8n-nodes-base.if",
      "typeVersion": 1,
      "position": [
        1120,
        700
      ]
    },
    {
      "parameters": {
        "conditions": {
          "string": [
            {
              "value1": "={{ $json['contact[tags]'] }}",
              "operation": "contains",
              "value2": "RS7 Pesquisa - C3"
            }
          ]
        }
      },
      "id": "203fe171-ad64-4cc7-8fa9-f78fb754b128",
      "name": "IF2",
      "type": "n8n-nodes-base.if",
      "typeVersion": 1,
      "position": [
        1180,
        960
      ]
    },
    {
      "parameters": {
        "conditions": {
          "string": [
            {
              "value1": "={{ $json.Nome }}",
              "operation": "isNotEmpty"
            }
          ]
        }
      },
      "id": "5581e1c8-b9f4-4219-9568-94a5ec4813b8",
      "name": "Filter",
      "type": "n8n-nodes-base.filter",
      "typeVersion": 1,
      "position": [
        1640,
        320
      ]
    },
    {
      "parameters": {
        "operation": "update",
        "documentId": {
          "__rl": true,
          "value": "130dJLqIJVkcFvqzEpK2M_bMpaGvhZMOLhDsWGuSJxy0",
          "mode": "list",
          "cachedResultName": "[ILA] [CICLO 3] Planilha Geral",
          "cachedResultUrl": "https://docs.google.com/spreadsheets/d/130dJLqIJVkcFvqzEpK2M_bMpaGvhZMOLhDsWGuSJxy0/edit?usp=drivesdk"
        },
        "sheetName": {
          "__rl": true,
          "value": 1930318114,
          "mode": "list",
          "cachedResultName": "[AUTO] Inscritos [AS7]",
          "cachedResultUrl": "https://docs.google.com/spreadsheets/d/130dJLqIJVkcFvqzEpK2M_bMpaGvhZMOLhDsWGuSJxy0/edit#gid=1930318114"
        },
        "columns": {
          "mappingMode": "defineBelow",
          "value": {
            "Email": "={{ $json.Email }}",
            "Recuperação de Pesquisa": "C1"
          },
          "matchingColumns": [
            "Email"
          ],
          "schema": [
            {
              "id": "Data",
              "displayName": "Data",
              "required": false,
              "defaultMatch": false,
              "display": true,
              "type": "string",
              "canBeUsedToMatch": true
            },
            {
              "id": "Chave (busca)",
              "displayName": "Chave (busca)",
              "required": false,
              "defaultMatch": false,
              "display": true,
              "type": "string",
              "canBeUsedToMatch": true,
              "removed": false
            },
            {
              "id": "Nome",
              "displayName": "Nome",
              "required": false,
              "defaultMatch": false,
              "display": true,
              "type": "string",
              "canBeUsedToMatch": true
            },
            {
              "id": "Email",
              "displayName": "Email",
              "required": false,
              "defaultMatch": false,
              "display": true,
              "type": "string",
              "canBeUsedToMatch": true,
              "removed": false
            },
            {
              "id": "Telefone",
              "displayName": "Telefone",
              "required": false,
              "defaultMatch": false,
              "display": true,
              "type": "string",
              "canBeUsedToMatch": true
            },
            {
              "id": "utm_source",
              "displayName": "utm_source",
              "required": false,
              "defaultMatch": false,
              "display": true,
              "type": "string",
              "canBeUsedToMatch": true
            },
            {
              "id": "utm_campaign",
              "displayName": "utm_campaign",
              "required": false,
              "defaultMatch": false,
              "display": true,
              "type": "string",
              "canBeUsedToMatch": true
            },
            {
              "id": "utm_medium",
              "displayName": "utm_medium",
              "required": false,
              "defaultMatch": false,
              "display": true,
              "type": "string",
              "canBeUsedToMatch": true
            },
            {
              "id": "utm_term",
              "displayName": "utm_term",
              "required": false,
              "defaultMatch": false,
              "display": true,
              "type": "string",
              "canBeUsedToMatch": true
            },
            {
              "id": "utm_content",
              "displayName": "utm_content",
              "required": false,
              "defaultMatch": false,
              "display": true,
              "type": "string",
              "canBeUsedToMatch": true
            },
            {
              "id": "temperatura",
              "displayName": "temperatura",
              "required": false,
              "defaultMatch": false,
              "display": true,
              "type": "string",
              "canBeUsedToMatch": true
            },
            {
              "id": "Página",
              "displayName": "Página",
              "required": false,
              "defaultMatch": false,
              "display": true,
              "type": "string",
              "canBeUsedToMatch": true
            },
            {
              "id": "Checkout direto",
              "displayName": "Checkout direto",
              "required": false,
              "defaultMatch": false,
              "display": true,
              "type": "string",
              "canBeUsedToMatch": true
            },
            {
              "id": "Idade",
              "displayName": "Idade",
              "required": false,
              "defaultMatch": false,
              "display": true,
              "type": "string",
              "canBeUsedToMatch": true
            },
            {
              "id": "O que espera da reunião",
              "displayName": "O que espera da reunião",
              "required": false,
              "defaultMatch": false,
              "display": true,
              "type": "string",
              "canBeUsedToMatch": true
            },
            {
              "id": "Investe em anúncios",
              "displayName": "Investe em anúncios",
              "required": false,
              "defaultMatch": false,
              "display": true,
              "type": "string",
              "canBeUsedToMatch": true
            },
            {
              "id": "Tempo de atuação",
              "displayName": "Tempo de atuação",
              "required": false,
              "defaultMatch": false,
              "display": true,
              "type": "string",
              "canBeUsedToMatch": true
            },
            {
              "id": "Procedimento que mais vende na clínica",
              "displayName": "Procedimento que mais vende na clínica",
              "required": false,
              "defaultMatch": false,
              "display": true,
              "type": "string",
              "canBeUsedToMatch": true
            },
            {
              "id": "Vendas por mês",
              "displayName": "Vendas por mês",
              "required": false,
              "defaultMatch": false,
              "display": true,
              "type": "string",
              "canBeUsedToMatch": true
            },
            {
              "id": "Costuma bater as metas do mês",
              "displayName": "Costuma bater as metas do mês",
              "required": false,
              "defaultMatch": false,
              "display": true,
              "type": "string",
              "canBeUsedToMatch": true
            },
            {
              "id": "Maior dificuldade para captar clientes",
              "displayName": "Maior dificuldade para captar clientes",
              "required": false,
              "defaultMatch": false,
              "display": true,
              "type": "string",
              "canBeUsedToMatch": true
            },
            {
              "id": "Faturamento ",
              "displayName": "Faturamento ",
              "required": false,
              "defaultMatch": false,
              "display": true,
              "type": "string",
              "canBeUsedToMatch": true
            },
            {
              "id": "Satisfeito com o faturamento atual",
              "displayName": "Satisfeito com o faturamento atual",
              "required": false,
              "defaultMatch": false,
              "display": true,
              "type": "string",
              "canBeUsedToMatch": true
            },
            {
              "id": "Quanto tempo conhece Ila & Nicole",
              "displayName": "Quanto tempo conhece Ila & Nicole",
              "required": false,
              "defaultMatch": false,
              "display": true,
              "type": "string",
              "canBeUsedToMatch": true,
              "removed": false
            },
            {
              "id": "Por onde conheceu Ila & Nicole",
              "displayName": "Por onde conheceu Ila & Nicole",
              "required": false,
              "defaultMatch": false,
              "display": true,
              "type": "string",
              "canBeUsedToMatch": true
            },
            {
              "id": "Nome Ingresso",
              "displayName": "Nome Ingresso",
              "required": false,
              "defaultMatch": false,
              "display": true,
              "type": "string",
              "canBeUsedToMatch": true
            },
            {
              "id": "Ingresso",
              "displayName": "Ingresso",
              "required": false,
              "defaultMatch": false,
              "display": true,
              "type": "string",
              "canBeUsedToMatch": true
            },
            {
              "id": "Ingresso Vip",
              "displayName": "Ingresso Vip",
              "required": false,
              "defaultMatch": false,
              "display": true,
              "type": "string",
              "canBeUsedToMatch": true
            },
            {
              "id": "Ticket",
              "displayName": "Ticket",
              "required": false,
              "defaultMatch": false,
              "display": true,
              "type": "string",
              "canBeUsedToMatch": true
            },
            {
              "id": "Chave(audio)",
              "displayName": "Chave(audio)",
              "required": false,
              "defaultMatch": false,
              "display": true,
              "type": "string",
              "canBeUsedToMatch": true
            },
            {
              "id": "Link audio",
              "displayName": "Link audio",
              "required": false,
              "defaultMatch": false,
              "display": true,
              "type": "string",
              "canBeUsedToMatch": true
            },
            {
              "id": "ID Clickup",
              "displayName": "ID Clickup",
              "required": false,
              "defaultMatch": false,
              "display": true,
              "type": "string",
              "canBeUsedToMatch": true
            },
            {
              "id": "Link Clickup",
              "displayName": "Link Clickup",
              "required": false,
              "defaultMatch": false,
              "display": true,
              "type": "string",
              "canBeUsedToMatch": true,
              "removed": false
            },
            {
              "id": "Respondeu Aplicação",
              "displayName": "Respondeu Aplicação",
              "required": false,
              "defaultMatch": false,
              "display": true,
              "type": "string",
              "canBeUsedToMatch": true
            },
            {
              "id": "Recuperação de Pesquisa",
              "displayName": "Recuperação de Pesquisa",
              "required": false,
              "defaultMatch": false,
              "display": true,
              "type": "string",
              "canBeUsedToMatch": true
            },
            {
              "id": "Respondeu Pesquisa",
              "displayName": "Respondeu Pesquisa",
              "required": false,
              "defaultMatch": false,
              "display": true,
              "type": "string",
              "canBeUsedToMatch": true,
              "removed": false
            },
            {
              "id": "url_ingresso",
              "displayName": "url_ingresso",
              "required": false,
              "defaultMatch": false,
              "display": true,
              "type": "string",
              "canBeUsedToMatch": true,
              "removed": false
            },
            {
              "id": "respondeu aviso data",
              "displayName": "respondeu aviso data",
              "required": false,
              "defaultMatch": false,
              "display": true,
              "type": "string",
              "canBeUsedToMatch": true,
              "removed": false
            },
            {
              "id": "Recebeu mensagem",
              "displayName": "Recebeu mensagem",
              "required": false,
              "defaultMatch": false,
              "display": true,
              "type": "string",
              "canBeUsedToMatch": true,
              "removed": false
            }
          ]
        },
        "options": {}
      },
      "id": "fc9a68a3-a748-4ec1-9e21-600082807b5d",
      "name": "Google Sheets1",
      "type": "n8n-nodes-base.googleSheets",
      "typeVersion": 4,
      "position": [
        1860,
        320
      ],
      "credentials": {
        "googleSheetsOAuth2Api": {
          "id": "aqyCUOYp9QE28Sw2",
          "name": "Cris - Libertas"
        }
      }
    },
    {
      "parameters": {
        "documentId": {
          "__rl": true,
          "value": "130dJLqIJVkcFvqzEpK2M_bMpaGvhZMOLhDsWGuSJxy0",
          "mode": "list",
          "cachedResultName": "[ILA] [CICLO 3] Planilha Geral",
          "cachedResultUrl": "https://docs.google.com/spreadsheets/d/130dJLqIJVkcFvqzEpK2M_bMpaGvhZMOLhDsWGuSJxy0/edit?usp=drivesdk"
        },
        "sheetName": {
          "__rl": true,
          "value": 1930318114,
          "mode": "list",
          "cachedResultName": "[AUTO] Inscritos [AS7]",
          "cachedResultUrl": "https://docs.google.com/spreadsheets/d/130dJLqIJVkcFvqzEpK2M_bMpaGvhZMOLhDsWGuSJxy0/edit#gid=1930318114"
        },
        "filtersUI": {
          "values": [
            {
              "lookupColumn": "Email",
              "lookupValue": "={{ $('Code3').item.json['contact[email]'] }}"
            }
          ]
        },
        "options": {}
      },
      "id": "b4701679-089a-4664-99c8-c388c031fd6c",
      "name": "Google Sheets2",
      "type": "n8n-nodes-base.googleSheets",
      "typeVersion": 4,
      "position": [
        1420,
        580
      ],
      "alwaysOutputData": true,
      "credentials": {
        "googleSheetsOAuth2Api": {
          "id": "aqyCUOYp9QE28Sw2",
          "name": "Cris - Libertas"
        }
      }
    },
    {
      "parameters": {
        "conditions": {
          "string": [
            {
              "value1": "={{ $json.Nome }}",
              "operation": "isNotEmpty"
            }
          ]
        }
      },
      "id": "a8ce31a7-0f3e-4ac3-aa6c-8d84ac5447e4",
      "name": "Filter1",
      "type": "n8n-nodes-base.filter",
      "typeVersion": 1,
      "position": [
        1640,
        580
      ]
    },
    {
      "parameters": {
        "operation": "update",
        "documentId": {
          "__rl": true,
          "value": "130dJLqIJVkcFvqzEpK2M_bMpaGvhZMOLhDsWGuSJxy0",
          "mode": "list",
          "cachedResultName": "[ILA] [CICLO 3] Planilha Geral",
          "cachedResultUrl": "https://docs.google.com/spreadsheets/d/130dJLqIJVkcFvqzEpK2M_bMpaGvhZMOLhDsWGuSJxy0/edit?usp=drivesdk"
        },
        "sheetName": {
          "__rl": true,
          "value": 1930318114,
          "mode": "list",
          "cachedResultName": "[AUTO] Inscritos [AS7]",
          "cachedResultUrl": "https://docs.google.com/spreadsheets/d/130dJLqIJVkcFvqzEpK2M_bMpaGvhZMOLhDsWGuSJxy0/edit#gid=1930318114"
        },
        "columns": {
          "mappingMode": "defineBelow",
          "value": {
            "Email": "={{ $json.Email }}",
            "Recuperação de Pesquisa": "C2"
          },
          "matchingColumns": [
            "Email"
          ],
          "schema": [
            {
              "id": "Data",
              "displayName": "Data",
              "required": false,
              "defaultMatch": false,
              "display": true,
              "type": "string",
              "canBeUsedToMatch": true
            },
            {
              "id": "Chave (busca)",
              "displayName": "Chave (busca)",
              "required": false,
              "defaultMatch": false,
              "display": true,
              "type": "string",
              "canBeUsedToMatch": true,
              "removed": false
            },
            {
              "id": "Nome",
              "displayName": "Nome",
              "required": false,
              "defaultMatch": false,
              "display": true,
              "type": "string",
              "canBeUsedToMatch": true
            },
            {
              "id": "Email",
              "displayName": "Email",
              "required": false,
              "defaultMatch": false,
              "display": true,
              "type": "string",
              "canBeUsedToMatch": true,
              "removed": false
            },
            {
              "id": "Telefone",
              "displayName": "Telefone",
              "required": false,
              "defaultMatch": false,
              "display": true,
              "type": "string",
              "canBeUsedToMatch": true
            },
            {
              "id": "utm_source",
              "displayName": "utm_source",
              "required": false,
              "defaultMatch": false,
              "display": true,
              "type": "string",
              "canBeUsedToMatch": true
            },
            {
              "id": "utm_campaign",
              "displayName": "utm_campaign",
              "required": false,
              "defaultMatch": false,
              "display": true,
              "type": "string",
              "canBeUsedToMatch": true
            },
            {
              "id": "utm_medium",
              "displayName": "utm_medium",
              "required": false,
              "defaultMatch": false,
              "display": true,
              "type": "string",
              "canBeUsedToMatch": true
            },
            {
              "id": "utm_term",
              "displayName": "utm_term",
              "required": false,
              "defaultMatch": false,
              "display": true,
              "type": "string",
              "canBeUsedToMatch": true
            },
            {
              "id": "utm_content",
              "displayName": "utm_content",
              "required": false,
              "defaultMatch": false,
              "display": true,
              "type": "string",
              "canBeUsedToMatch": true
            },
            {
              "id": "temperatura",
              "displayName": "temperatura",
              "required": false,
              "defaultMatch": false,
              "display": true,
              "type": "string",
              "canBeUsedToMatch": true
            },
            {
              "id": "Página",
              "displayName": "Página",
              "required": false,
              "defaultMatch": false,
              "display": true,
              "type": "string",
              "canBeUsedToMatch": true
            },
            {
              "id": "Checkout direto",
              "displayName": "Checkout direto",
              "required": false,
              "defaultMatch": false,
              "display": true,
              "type": "string",
              "canBeUsedToMatch": true
            },
            {
              "id": "Idade",
              "displayName": "Idade",
              "required": false,
              "defaultMatch": false,
              "display": true,
              "type": "string",
              "canBeUsedToMatch": true
            },
            {
              "id": "O que espera da reunião",
              "displayName": "O que espera da reunião",
              "required": false,
              "defaultMatch": false,
              "display": true,
              "type": "string",
              "canBeUsedToMatch": true
            },
            {
              "id": "Investe em anúncios",
              "displayName": "Investe em anúncios",
              "required": false,
              "defaultMatch": false,
              "display": true,
              "type": "string",
              "canBeUsedToMatch": true
            },
            {
              "id": "Tempo de atuação",
              "displayName": "Tempo de atuação",
              "required": false,
              "defaultMatch": false,
              "display": true,
              "type": "string",
              "canBeUsedToMatch": true
            },
            {
              "id": "Procedimento que mais vende na clínica",
              "displayName": "Procedimento que mais vende na clínica",
              "required": false,
              "defaultMatch": false,
              "display": true,
              "type": "string",
              "canBeUsedToMatch": true
            },
            {
              "id": "Vendas por mês",
              "displayName": "Vendas por mês",
              "required": false,
              "defaultMatch": false,
              "display": true,
              "type": "string",
              "canBeUsedToMatch": true
            },
            {
              "id": "Costuma bater as metas do mês",
              "displayName": "Costuma bater as metas do mês",
              "required": false,
              "defaultMatch": false,
              "display": true,
              "type": "string",
              "canBeUsedToMatch": true
            },
            {
              "id": "Maior dificuldade para captar clientes",
              "displayName": "Maior dificuldade para captar clientes",
              "required": false,
              "defaultMatch": false,
              "display": true,
              "type": "string",
              "canBeUsedToMatch": true
            },
            {
              "id": "Faturamento ",
              "displayName": "Faturamento ",
              "required": false,
              "defaultMatch": false,
              "display": true,
              "type": "string",
              "canBeUsedToMatch": true
            },
            {
              "id": "Satisfeito com o faturamento atual",
              "displayName": "Satisfeito com o faturamento atual",
              "required": false,
              "defaultMatch": false,
              "display": true,
              "type": "string",
              "canBeUsedToMatch": true
            },
            {
              "id": "Quanto tempo conhece Ila & Nicole",
              "displayName": "Quanto tempo conhece Ila & Nicole",
              "required": false,
              "defaultMatch": false,
              "display": true,
              "type": "string",
              "canBeUsedToMatch": true,
              "removed": false
            },
            {
              "id": "Por onde conheceu Ila & Nicole",
              "displayName": "Por onde conheceu Ila & Nicole",
              "required": false,
              "defaultMatch": false,
              "display": true,
              "type": "string",
              "canBeUsedToMatch": true
            },
            {
              "id": "Nome Ingresso",
              "displayName": "Nome Ingresso",
              "required": false,
              "defaultMatch": false,
              "display": true,
              "type": "string",
              "canBeUsedToMatch": true
            },
            {
              "id": "Ingresso",
              "displayName": "Ingresso",
              "required": false,
              "defaultMatch": false,
              "display": true,
              "type": "string",
              "canBeUsedToMatch": true
            },
            {
              "id": "Ingresso Vip",
              "displayName": "Ingresso Vip",
              "required": false,
              "defaultMatch": false,
              "display": true,
              "type": "string",
              "canBeUsedToMatch": true
            },
            {
              "id": "Ticket",
              "displayName": "Ticket",
              "required": false,
              "defaultMatch": false,
              "display": true,
              "type": "string",
              "canBeUsedToMatch": true
            },
            {
              "id": "Chave(audio)",
              "displayName": "Chave(audio)",
              "required": false,
              "defaultMatch": false,
              "display": true,
              "type": "string",
              "canBeUsedToMatch": true
            },
            {
              "id": "Link audio",
              "displayName": "Link audio",
              "required": false,
              "defaultMatch": false,
              "display": true,
              "type": "string",
              "canBeUsedToMatch": true
            },
            {
              "id": "ID Clickup",
              "displayName": "ID Clickup",
              "required": false,
              "defaultMatch": false,
              "display": true,
              "type": "string",
              "canBeUsedToMatch": true
            },
            {
              "id": "Link Clickup",
              "displayName": "Link Clickup",
              "required": false,
              "defaultMatch": false,
              "display": true,
              "type": "string",
              "canBeUsedToMatch": true,
              "removed": false
            },
            {
              "id": "Respondeu Aplicação",
              "displayName": "Respondeu Aplicação",
              "required": false,
              "defaultMatch": false,
              "display": true,
              "type": "string",
              "canBeUsedToMatch": true
            },
            {
              "id": "Recuperação de Pesquisa",
              "displayName": "Recuperação de Pesquisa",
              "required": false,
              "defaultMatch": false,
              "display": true,
              "type": "string",
              "canBeUsedToMatch": true
            },
            {
              "id": "Respondeu Pesquisa",
              "displayName": "Respondeu Pesquisa",
              "required": false,
              "defaultMatch": false,
              "display": true,
              "type": "string",
              "canBeUsedToMatch": true,
              "removed": false
            },
            {
              "id": "url_ingresso",
              "displayName": "url_ingresso",
              "required": false,
              "defaultMatch": false,
              "display": true,
              "type": "string",
              "canBeUsedToMatch": true,
              "removed": false
            },
            {
              "id": "respondeu aviso data",
              "displayName": "respondeu aviso data",
              "required": false,
              "defaultMatch": false,
              "display": true,
              "type": "string",
              "canBeUsedToMatch": true,
              "removed": false
            },
            {
              "id": "Recebeu mensagem",
              "displayName": "Recebeu mensagem",
              "required": false,
              "defaultMatch": false,
              "display": true,
              "type": "string",
              "canBeUsedToMatch": true,
              "removed": false
            }
          ]
        },
        "options": {}
      },
      "id": "53804c36-1793-4e2a-b338-6a9ec8635100",
      "name": "Google Sheets3",
      "type": "n8n-nodes-base.googleSheets",
      "typeVersion": 4,
      "position": [
        1860,
        580
      ],
      "credentials": {
        "googleSheetsOAuth2Api": {
          "id": "aqyCUOYp9QE28Sw2",
          "name": "Cris - Libertas"
        }
      }
    },
    {
      "parameters": {
        "documentId": {
          "__rl": true,
          "value": "130dJLqIJVkcFvqzEpK2M_bMpaGvhZMOLhDsWGuSJxy0",
          "mode": "list",
          "cachedResultName": "[ILA] [CICLO 3] Planilha Geral",
          "cachedResultUrl": "https://docs.google.com/spreadsheets/d/130dJLqIJVkcFvqzEpK2M_bMpaGvhZMOLhDsWGuSJxy0/edit?usp=drivesdk"
        },
        "sheetName": {
          "__rl": true,
          "value": 1930318114,
          "mode": "list",
          "cachedResultName": "[AUTO] Inscritos [AS7]",
          "cachedResultUrl": "https://docs.google.com/spreadsheets/d/130dJLqIJVkcFvqzEpK2M_bMpaGvhZMOLhDsWGuSJxy0/edit#gid=1930318114"
        },
        "filtersUI": {
          "values": [
            {
              "lookupColumn": "Email",
              "lookupValue": "={{ $('Code3').item.json['contact[email]'] }}"
            }
          ]
        },
        "options": {}
      },
      "id": "b3d3050f-1078-4c5f-9bd0-edc188335b6f",
      "name": "Google Sheets4",
      "type": "n8n-nodes-base.googleSheets",
      "typeVersion": 4,
      "position": [
        1420,
        840
      ],
      "alwaysOutputData": true,
      "credentials": {
        "googleSheetsOAuth2Api": {
          "id": "aqyCUOYp9QE28Sw2",
          "name": "Cris - Libertas"
        }
      }
    },
    {
      "parameters": {
        "conditions": {
          "string": [
            {
              "value1": "={{ $json.Nome }}",
              "operation": "isNotEmpty"
            }
          ]
        }
      },
      "id": "f69c5012-5c8c-4806-8794-62f80c980cf7",
      "name": "Filter2",
      "type": "n8n-nodes-base.filter",
      "typeVersion": 1,
      "position": [
        1640,
        840
      ]
    },
    {
      "parameters": {
        "operation": "update",
        "documentId": {
          "__rl": true,
          "value": "1aCecSlhAwfyA4HZfcLP8DyvzQkqiBiiLkHLWi8xG5Bc",
          "mode": "list",
          "cachedResultName": " [ILA] [CICLO 2] Planilha Geral",
          "cachedResultUrl": "https://docs.google.com/spreadsheets/d/1aCecSlhAwfyA4HZfcLP8DyvzQkqiBiiLkHLWi8xG5Bc/edit?usp=drivesdk"
        },
        "sheetName": {
          "__rl": true,
          "value": 1423227382,
          "mode": "list",
          "cachedResultName": "[AUTO] Inscritos [AS5]",
          "cachedResultUrl": "https://docs.google.com/spreadsheets/d/1aCecSlhAwfyA4HZfcLP8DyvzQkqiBiiLkHLWi8xG5Bc/edit#gid=1423227382"
        },
        "columns": {
          "mappingMode": "defineBelow",
          "value": {
            "Email": "={{ $json.Email }}",
            "Recuperação de Pesquisa": "C3"
          },
          "matchingColumns": [
            "Email"
          ],
          "schema": [
            {
              "id": "Data",
              "displayName": "Data",
              "required": false,
              "defaultMatch": false,
              "display": true,
              "type": "string",
              "canBeUsedToMatch": true
            },
            {
              "id": "Chave(busca)",
              "displayName": "Chave(busca)",
              "required": false,
              "defaultMatch": false,
              "display": true,
              "type": "string",
              "canBeUsedToMatch": true
            },
            {
              "id": "Nome",
              "displayName": "Nome",
              "required": false,
              "defaultMatch": false,
              "display": true,
              "type": "string",
              "canBeUsedToMatch": true
            },
            {
              "id": "Email",
              "displayName": "Email",
              "required": false,
              "defaultMatch": false,
              "display": true,
              "type": "string",
              "canBeUsedToMatch": true,
              "removed": false
            },
            {
              "id": "Telefone",
              "displayName": "Telefone",
              "required": false,
              "defaultMatch": false,
              "display": true,
              "type": "string",
              "canBeUsedToMatch": true
            },
            {
              "id": "utm_source",
              "displayName": "utm_source",
              "required": false,
              "defaultMatch": false,
              "display": true,
              "type": "string",
              "canBeUsedToMatch": true
            },
            {
              "id": "utm_campaign",
              "displayName": "utm_campaign",
              "required": false,
              "defaultMatch": false,
              "display": true,
              "type": "string",
              "canBeUsedToMatch": true
            },
            {
              "id": "utm_medium",
              "displayName": "utm_medium",
              "required": false,
              "defaultMatch": false,
              "display": true,
              "type": "string",
              "canBeUsedToMatch": true
            },
            {
              "id": "utm_term",
              "displayName": "utm_term",
              "required": false,
              "defaultMatch": false,
              "display": true,
              "type": "string",
              "canBeUsedToMatch": true
            },
            {
              "id": "utm_content",
              "displayName": "utm_content",
              "required": false,
              "defaultMatch": false,
              "display": true,
              "type": "string",
              "canBeUsedToMatch": true
            },
            {
              "id": "temperatura",
              "displayName": "temperatura",
              "required": false,
              "defaultMatch": false,
              "display": true,
              "type": "string",
              "canBeUsedToMatch": true
            },
            {
              "id": "Página",
              "displayName": "Página",
              "required": false,
              "defaultMatch": false,
              "display": true,
              "type": "string",
              "canBeUsedToMatch": true
            },
            {
              "id": "Checkout direto",
              "displayName": "Checkout direto",
              "required": false,
              "defaultMatch": false,
              "display": true,
              "type": "string",
              "canBeUsedToMatch": true
            },
            {
              "id": "Idade",
              "displayName": "Idade",
              "required": false,
              "defaultMatch": false,
              "display": true,
              "type": "string",
              "canBeUsedToMatch": true
            },
            {
              "id": "O que espera da reunião",
              "displayName": "O que espera da reunião",
              "required": false,
              "defaultMatch": false,
              "display": true,
              "type": "string",
              "canBeUsedToMatch": true
            },
            {
              "id": "Investe em anúncios",
              "displayName": "Investe em anúncios",
              "required": false,
              "defaultMatch": false,
              "display": true,
              "type": "string",
              "canBeUsedToMatch": true
            },
            {
              "id": "Tempo de atuação",
              "displayName": "Tempo de atuação",
              "required": false,
              "defaultMatch": false,
              "display": true,
              "type": "string",
              "canBeUsedToMatch": true
            },
            {
              "id": "Procedimento que mais vende na clínica",
              "displayName": "Procedimento que mais vende na clínica",
              "required": false,
              "defaultMatch": false,
              "display": true,
              "type": "string",
              "canBeUsedToMatch": true
            },
            {
              "id": "Vendas por mês",
              "displayName": "Vendas por mês",
              "required": false,
              "defaultMatch": false,
              "display": true,
              "type": "string",
              "canBeUsedToMatch": true
            },
            {
              "id": "Costuma bater as metas do mês",
              "displayName": "Costuma bater as metas do mês",
              "required": false,
              "defaultMatch": false,
              "display": true,
              "type": "string",
              "canBeUsedToMatch": true
            },
            {
              "id": "Maior dificuldade para captar clientes",
              "displayName": "Maior dificuldade para captar clientes",
              "required": false,
              "defaultMatch": false,
              "display": true,
              "type": "string",
              "canBeUsedToMatch": true
            },
            {
              "id": "Faturamento ",
              "displayName": "Faturamento ",
              "required": false,
              "defaultMatch": false,
              "display": true,
              "type": "string",
              "canBeUsedToMatch": true
            },
            {
              "id": "Satisfeito com o faturamento atual",
              "displayName": "Satisfeito com o faturamento atual",
              "required": false,
              "defaultMatch": false,
              "display": true,
              "type": "string",
              "canBeUsedToMatch": true
            },
            {
              "id": "Quanto tempo conhece Ila & Nicolo",
              "displayName": "Quanto tempo conhece Ila & Nicolo",
              "required": false,
              "defaultMatch": false,
              "display": true,
              "type": "string",
              "canBeUsedToMatch": true
            },
            {
              "id": "Por onde conheceu Ila & Nicole",
              "displayName": "Por onde conheceu Ila & Nicole",
              "required": false,
              "defaultMatch": false,
              "display": true,
              "type": "string",
              "canBeUsedToMatch": true
            },
            {
              "id": "Nome Ingresso",
              "displayName": "Nome Ingresso",
              "required": false,
              "defaultMatch": false,
              "display": true,
              "type": "string",
              "canBeUsedToMatch": true
            },
            {
              "id": "Ingresso",
              "displayName": "Ingresso",
              "required": false,
              "defaultMatch": false,
              "display": true,
              "type": "string",
              "canBeUsedToMatch": true
            },
            {
              "id": "Ingresso Vip",
              "displayName": "Ingresso Vip",
              "required": false,
              "defaultMatch": false,
              "display": true,
              "type": "string",
              "canBeUsedToMatch": true
            },
            {
              "id": "CRC 1",
              "displayName": "CRC 1",
              "required": false,
              "defaultMatch": false,
              "display": true,
              "type": "string",
              "canBeUsedToMatch": true
            },
            {
              "id": "CRC 2",
              "displayName": "CRC 2",
              "required": false,
              "defaultMatch": false,
              "display": true,
              "type": "string",
              "canBeUsedToMatch": true
            },
            {
              "id": "CRC 3",
              "displayName": "CRC 3",
              "required": false,
              "defaultMatch": false,
              "display": true,
              "type": "string",
              "canBeUsedToMatch": true
            },
            {
              "id": "Ingressos CRC'S",
              "displayName": "Ingressos CRC'S",
              "required": false,
              "defaultMatch": false,
              "display": true,
              "type": "string",
              "canBeUsedToMatch": true
            },
            {
              "id": "Chave(audio)",
              "displayName": "Chave(audio)",
              "required": false,
              "defaultMatch": false,
              "display": true,
              "type": "string",
              "canBeUsedToMatch": true
            },
            {
              "id": "Link audio",
              "displayName": "Link audio",
              "required": false,
              "defaultMatch": false,
              "display": true,
              "type": "string",
              "canBeUsedToMatch": true
            },
            {
              "id": "ID Clickup",
              "displayName": "ID Clickup",
              "required": false,
              "defaultMatch": false,
              "display": true,
              "type": "string",
              "canBeUsedToMatch": true
            },
            {
              "id": "Ticket",
              "displayName": "Ticket",
              "required": false,
              "defaultMatch": false,
              "display": true,
              "type": "string",
              "canBeUsedToMatch": true
            },
            {
              "id": "Nome áudio",
              "displayName": "Nome áudio",
              "required": false,
              "defaultMatch": false,
              "display": true,
              "type": "string",
              "canBeUsedToMatch": true
            },
            {
              "id": "Áudio",
              "displayName": "Áudio",
              "required": false,
              "defaultMatch": false,
              "display": true,
              "type": "string",
              "canBeUsedToMatch": true
            },
            {
              "id": "Respondeu Aplicação",
              "displayName": "Respondeu Aplicação",
              "required": false,
              "defaultMatch": false,
              "display": true,
              "type": "string",
              "canBeUsedToMatch": true
            },
            {
              "id": "Recuperação de Pesquisa",
              "displayName": "Recuperação de Pesquisa",
              "required": false,
              "defaultMatch": false,
              "display": true,
              "type": "string",
              "canBeUsedToMatch": true
            }
          ]
        },
        "options": {}
      },
      "id": "cf7fcb6f-6acb-4d6e-b010-a6a7b30fbac0",
      "name": "Google Sheets5",
      "type": "n8n-nodes-base.googleSheets",
      "typeVersion": 4,
      "position": [
        1860,
        840
      ],
      "credentials": {
        "googleSheetsOAuth2Api": {
          "id": "aqyCUOYp9QE28Sw2",
          "name": "Cris - Libertas"
        }
      }
    },
    {
      "parameters": {
        "httpMethod": "POST",
        "path": "4f988361-ad19-4d10-8241-d5b59bdc6bf2",
        "options": {}
      },
      "id": "58d81322-62a9-492f-b270-d4dcd8443435",
      "name": "Webhook",
      "type": "n8n-nodes-base.webhook",
      "typeVersion": 1,
      "position": [
        480,
        460
      ],
      "webhookId": "4f988361-ad19-4d10-8241-d5b59bdc6bf2"
    },
    {
      "parameters": {
        "method": "POST",
        "url": "https://api.z-api.io/instances/3C1825917D649026AAA446A65441921E/token/92B58C5DAD3489D5AD780116/send-text",
        "sendBody": true,
        "bodyParameters": {
          "parameters": [
            {
              "name": "phone",
              "value": "={{ $('Code3').item.json['contact[phone]'] }}"
            },
            {
              "name": "message",
              "value": "={{ $('Code3').item.json['contact[first_name]'] }}, Eu e a Nicole estamos prontas para te mostrar o caminho de como faturar de 100 a 300k por mês no seu consultório. "
            },
            {
              "name": "delayMessage",
              "value": "={{ Math.floor(Math.random()* 11) + 5 }}"
            },
            {
              "name": "delayTyping",
              "value": "={{ Math.floor(Math.random()* 11) + 5 }}"
            }
          ]
        },
        "options": {}
      },
      "id": "f7a5f1f6-bec7-43d3-a63a-b44fe8c659b5",
      "name": "ENVIA C1",
      "type": "n8n-nodes-base.httpRequest",
      "typeVersion": 4.1,
      "position": [
        2060,
        320
      ]
    },
    {
      "parameters": {
        "method": "POST",
        "url": "https://api.z-api.io/instances/3C1825917D649026AAA446A65441921E/token/92B58C5DAD3489D5AD780116/send-text",
        "sendBody": true,
        "bodyParameters": {
          "parameters": [
            {
              "name": "phone",
              "value": "={{ $('Code3').item.json['contact[phone]'] }}"
            },
            {
              "name": "message",
              "value": "=E nós queremos te conhecer melhor e entender o seu momento atual para garantir que você consiga aproveitar o conteúdo ao máximo."
            },
            {
              "name": "delayMessage",
              "value": "={{ Math.floor(Math.random()* 11) + 5 }}"
            },
            {
              "name": "delayTyping",
              "value": "=3"
            }
          ]
        },
        "options": {}
      },
      "id": "bcfe8083-d84b-474a-8a15-d33483b05059",
      "name": "ENVIA C1.1",
      "type": "n8n-nodes-base.httpRequest",
      "typeVersion": 4.1,
      "position": [
        2300,
        320
      ]
    },
    {
      "parameters": {
        "method": "POST",
        "url": "https://api.z-api.io/instances/3C1825917D649026AAA446A65441921E/token/92B58C5DAD3489D5AD780116/send-text",
        "sendBody": true,
        "bodyParameters": {
          "parameters": [
            {
              "name": "phone",
              "value": "={{ $('Code3').item.json['contact[phone]'] }}"
            },
            {
              "name": "message",
              "value": "=Oi,  {{ $('Code3').item.json['contact[first_name]'] }}, tudo bem? Tô passando aqui pra saber se você conseguiu responder a pesquisa que te enviei na última mensagem?"
            },
            {
              "name": "delayMessage",
              "value": "={{ Math.floor(Math.random()* 11) + 5 }}"
            },
            {
              "name": "delayTyping",
              "value": "=3"
            }
          ]
        },
        "options": {}
      },
      "id": "8ebc5c92-8b18-421c-97c9-2f8a9db8f4c0",
      "name": "ENVIA C",
      "type": "n8n-nodes-base.httpRequest",
      "typeVersion": 4.1,
      "position": [
        2060,
        580
      ]
    },
    {
      "parameters": {
        "method": "POST",
        "url": "https://api.z-api.io/instances/3C1825917D649026AAA446A65441921E/token/92B58C5DAD3489D5AD780116/send-link",
        "sendBody": true,
        "bodyParameters": {
          "parameters": [
            {
              "name": "phone",
              "value": "={{ $('Code3').item.json['contact[phone]'] }}"
            },
            {
              "name": "message",
              "value": "=Para isso, é muito importante que você responda essa pesquisa (leva menos de 2 minutos). Posso contar com você?\n\nEsse aqui é o link da pesquisa:\nhttps://bit.ly/inscritos-pesquisa"
            },
            {
              "name": "delayMessage",
              "value": "={{ Math.floor(Math.random()* 11) + 5 }}"
            },
            {
              "name": "delayTyping",
              "value": "=3"
            },
            {
              "name": "image",
              "value": "=https://dentistapower.com.br/wp-content/uploads/2023/08/BG_INVESTIMENTO-768x1364.webp"
            },
            {
              "name": "linkUrl",
              "value": "=https://bit.ly/inscritos-pesquisa"
            },
            {
              "name": "title",
              "value": "Queremos te conhecer melhor"
            },
            {
              "name": "linkDescription",
              "value": "Dura apenas 2 minutos! "
            }
          ]
        },
        "options": {}
      },
      "id": "8a98c8ac-d0ee-47ff-a006-02efdb2a8d42",
      "name": "ENVIA C1.2",
      "type": "n8n-nodes-base.httpRequest",
      "typeVersion": 4.1,
      "position": [
        2540,
        320
      ]
    }
  ],
  "pinData": {
    "Webhook": [
      {
        "json": {
          "headers": {
            "host": "n8n.marcosfoks.com.br",
            "user-agent": "GuzzleHttp/6.5.5 curl/8.3.0 PHP/7.4.33",
            "content-length": "5210",
            "accept-encoding": "gzip",
            "cdn-loop": "cloudflare",
            "cf-connecting-ip": "3.220.243.205",
            "cf-ipcountry": "US",
            "cf-ray": "825f4ca91eab0836-IAD",
            "cf-visitor": "{\"scheme\":\"https\"}",
            "content-type": "application/x-www-form-urlencoded",
            "x-forwarded-for": "172.70.39.121",
            "x-forwarded-host": "n8n.marcosfoks.com.br",
            "x-forwarded-port": "443",
            "x-forwarded-proto": "https",
            "x-forwarded-server": "af9052d35998",
            "x-real-ip": "172.70.39.121"
          },
          "params": {},
          "query": {},
          "body": {
            "contact[id]": "1782",
            "contact[email]": "crisrs5@gmail.com",
            "contact[first_name]": "Cris",
            "contact[last_name]": "",
            "contact[phone]": "5581993515055",
            "contact[orgname]": "",
            "contact[customer_acct_name]": "",
            "contact[tags]": "[RS5] Número Inválido RS5 Pesquisa - C1",
            "contact[ip4]": "0.0.0.0",
            "contact[fields][status_de_recuperao]": "",
            "contact[fields][kap_abandono_de_carrinho_date]": "",
            "contact[fields][kap_refund_date]": "",
            "contact[fields][kap_purchase_date]": "",
            "contact[fields][ap_s1_subscribe_date]": "",
            "contact[fields][utmsources1ap]": "",
            "contact[fields][utmcampaigns1ap]": "",
            "contact[fields][utmmediums1ap]": "",
            "contact[fields][utmcontents1ap]": "",
            "contact[fields][utmterms1ap]": "",
            "contact[fields][aps1_refund_date]": "",
            "contact[fields][aps1_purchase_date]": "",
            "contact[fields][tf_20_aguardando_pagamento_date]": "",
            "contact[fields][tf_20_compra_cancelada_date]": "",
            "contact[fields][tf20_initiate_checkout_date]": "",
            "contact[fields][tf20_compra_cancelada_date]": "",
            "contact[fields][tf20_initiate_checkout_date_1]": "",
            "contact[fields][tf20_pix_date]": "",
            "contact[fields][tf20_compra_reembolsada_date]": "",
            "contact[fields][utmsourcetf20]": "",
            "contact[fields][utmcampaigntf20]": "",
            "contact[fields][utmmediumtf20]": "",
            "contact[fields][utmtermtf20]": "",
            "contact[fields][utmcontenttf20]": "",
            "contact[fields][utm_source]": "",
            "contact[fields][utm_campaign]": "",
            "contact[fields][utm_medium]": "",
            "contact[fields][utm_content]": "",
            "contact[fields][utm_term]": "",
            "contact[fields][treinamento_initiate_checkout]": "",
            "contact[fields][utmsourcers1]": "",
            "contact[fields][utmcampaignrs1]": "",
            "contact[fields][utmmediumrs1]": "",
            "contact[fields][utmcontentrs1]": "",
            "contact[fields][utmtermrs1]": "",
            "contact[fields][rs1_subscribe_date]": "",
            "contact[fields][rs1_temperatura]": "",
            "contact[fields][rs1_pgina_capt]": "",
            "contact[fields][rs1_initiatecheckout_date]": "",
            "contact[fields][rs1_abandonou_carrinho_date]": "",
            "contact[fields][rs1_checkout_direto]": "",
            "contact[fields][name]": "",
            "contact[fields][nmero]": "",
            "contact[fields][rs1_ingresso_contato_realizado]": "",
            "contact[fields][rs1_pix_emitido_date]": "",
            "contact[fields][rs1_compra_cancelada_date]": "",
            "contact[fields][qrcode]": "",
            "contact[fields][imgqrcode]": "",
            "contact[fields][utmsourcers2]": "",
            "contact[fields][utmcampaignrs2]": "",
            "contact[fields][utmmediumrs2]": "",
            "contact[fields][utmcontentrs2]": "",
            "contact[fields][utmtermrs2]": "",
            "contact[fields][rs2_temperatura]": "",
            "contact[fields][rs2_pgina_capt]": "",
            "contact[fields][rs2_subscribe_date]": "",
            "contact[fields][rs2_initiatecheckout_date]": "",
            "contact[fields][rs2_pix_emitido_date]": "",
            "contact[fields][rs2_compra_cancelada_date]": "",
            "contact[fields][rs2_checkout_direto]": "",
            "contact[fields][rs2_ingresso_respondeu_recuperao]": "",
            "contact[fields][rs2_recebeu_recuperao]": "",
            "contact[fields][rs2_compra_reclamada_date]": "",
            "contact[fields][utmsourcers3]": "",
            "contact[fields][utmcampaignrs3]": "",
            "contact[fields][utmmediumrs3]": "",
            "contact[fields][utmcontentrs3]": "",
            "contact[fields][utmtermrs3]": "",
            "contact[fields][rs3_temperatura]": "",
            "contact[fields][rs3_pgina_capt]": "",
            "contact[fields][rs3_subscribe_date]": "",
            "contact[fields][rs3_initiatecheckout_date]": "",
            "contact[fields][rs3_pix_emitido_date]": "",
            "contact[fields][rs3_compra_cancelada_date]": "",
            "contact[fields][rs3_checkout_direto]": "",
            "contact[fields][rs3_ingresso_respondeu_recuperao]": "",
            "contact[fields][rs3_compra_reclamada_date]": "",
            "contact[fields][rs3_recebeu_recuperao]": "",
            "contact[fields][utmsourcers4]": "",
            "contact[fields][utmcampaignrs4]": "",
            "contact[fields][utmmediumrs4]": "",
            "contact[fields][utmcontentrs4]": "",
            "contact[fields][utmtermrs4]": "",
            "contact[fields][rs4_temperatura]": "",
            "contact[fields][rs4_pgina_capt]": "",
            "contact[fields][rs4_subscribe_date]": "",
            "contact[fields][rs4_initiatecheckout_date]": "",
            "contact[fields][rs4_pix_emitido_date]": "",
            "contact[fields][rs4_compra_cancelada_date]": "",
            "contact[fields][rs4_checkout_direto]": "",
            "contact[fields][rs4_ingresso_respondeu_recuperao]": "",
            "contact[fields][rs4_compra_reclamada_date]": "",
            "contact[fields][rs4_recebeu_recuperao]": "",
            "contact[fields][utmsourcers5]": "adsfb",
            "contact[fields][utmcampaignrs5]": "as5",
            "contact[fields][utmmediumrs5]": "teste",
            "contact[fields][utmcontentrs5]": "teste",
            "contact[fields][utmtermrs5]": "teste",
            "contact[fields][rs5_temperatura]": "quente",
            "contact[fields][rs5_pgina_capt]": "teste",
            "contact[fields][rs5_subscribe_date]": "2023-10-24",
            "contact[fields][rs5_initiatecheckout_date]": "2023-10-23",
            "contact[fields][rs5_pix_emitido_date]": "2023-10-23",
            "contact[fields][rs5_compra_cancelada_date]": "2023-10-25",
            "contact[fields][rs5_checkout_direto]": "não",
            "contact[fields][rs5_ingresso_respondeu_recuperao]": "sim",
            "contact[fields][rs5_compra_reclamada_date]": "2023-10-24",
            "contact[fields][rs5_recebeu_recuperao]": "sim",
            "seriesid": "52"
          }
        }
      }
    ]
  },
  "settings": {
    "executionOrder": "v1"
  },
  "staticData": null,
  "tags": [
    {
      "createdAt": "2023-10-12T03:16:03.155Z",
      "updatedAt": "2023-10-12T03:16:03.155Z",
      "id": "RsdI5HyLiEx96UXQ",
      "name": "RS"
    },
    {
      "createdAt": "2023-11-14T13:15:56.505Z",
      "updatedAt": "2023-11-14T13:15:56.505Z",
      "id": "oQQciN9UP3MQOsdN",
      "name": "Recup"
    }
  ],
  "triggerCount": 1,
  "updatedAt": "2024-02-14T02:52:37.000Z",
  "versionId": "2f9e7bf9-7016-42b1-9001-1d24cbc05a26"
}